rega-0.1.1.data/scripts/rega.py
src/__init__.py
src/rega.py
rega-0.1.1.dist-info/METADATA
rega-0.1.1.dist-info/WHEEL
rega-0.1.1.dist-info/entry_points.txt
rega-0.1.1.dist-info/top_level.txt
rega-0.1.1.dist-info/RECORD
